MANIFEST.in
README.txt
setup.cfg
setup.py
atreal/__init__.py
atreal/__init__.pyc
atreal.richfile.metadata.egg-info/PKG-INFO
atreal.richfile.metadata.egg-info/SOURCES.txt
atreal.richfile.metadata.egg-info/dependency_links.txt
atreal.richfile.metadata.egg-info/entry_points.txt
atreal.richfile.metadata.egg-info/namespace_packages.txt
atreal.richfile.metadata.egg-info/not-zip-safe
atreal.richfile.metadata.egg-info/requires.txt
atreal.richfile.metadata.egg-info/top_level.txt
atreal/richfile/__init__.py
atreal/richfile/__init__.pyc
atreal/richfile/metadata/__init__.py
atreal/richfile/metadata/adapters.py
atreal/richfile/metadata/configure.zcml
atreal/richfile/metadata/events.py
atreal/richfile/metadata/extractors.py
atreal/richfile/metadata/extractors_mimetypes.py
atreal/richfile/metadata/interfaces.py
atreal/richfile/metadata/browser/__init__.py
atreal/richfile/metadata/browser/configure.zcml
atreal/richfile/metadata/browser/controlpanel.pt
atreal/richfile/metadata/browser/controlpanel.py
atreal/richfile/metadata/browser/metadata.kss
atreal/richfile/metadata/browser/richfilemetadata_icon.png
atreal/richfile/metadata/browser/view.pt
atreal/richfile/metadata/browser/viewlet.pt
atreal/richfile/metadata/browser/viewlets.py
atreal/richfile/metadata/browser/views.py
atreal/richfile/metadata/lib/EXIF.py
atreal/richfile/metadata/lib/__init__.py
atreal/richfile/metadata/locales/atreal.richfile.metadata.pot
atreal/richfile/metadata/locales/fr/LC_MESSAGES/atreal.richfile.metadata.po
atreal/richfile/metadata/profiles/default/actionicons.xml
atreal/richfile/metadata/profiles/default/browserlayer.xml
atreal/richfile/metadata/profiles/default/componentregistry.xml
atreal/richfile/metadata/profiles/default/controlpanel.xml
atreal/richfile/metadata/profiles/default/kssregistry.xml
atreal/richfile/metadata/profiles/default/metadata.xml