Metadata-Version: 1.0
Name: atreal.richfile.metadata
Version: 1.0.0beta1
Summary: A plugin for atreal.richfile that extracts metadata
Home-page: http://www.atreal.net
Author: atReal
Author-email: contact@atreal.net
License: GPL
Keywords: atreal plone richfile metadata
Platform: UNKNOWN
Classifier: Framework :: Plone
Classifier: Programming Language :: Python
Classifier: Topic :: Software Development :: Libraries :: Python Modules
